bit-online-code-helper/__init__.py
bit-online-code-helper/main.py
bit-online-code-helper/bitonline/BITOnlineManager.py
bit-online-code-helper/bitonline/LocalTestCodeManager.py
bit-online-code-helper/bitonline/LoginManager.py
bit-online-code-helper/bitonline/OnlineTestCodeManager.py
bit-online-code-helper/bitonline/ProblemManager.py
bit-online-code-helper/bitonline/__init__.py
bit-online-code-helper/cli/ArgsParser.py
bit-online-code-helper/cli/__init__.py
bit-online-code-helper/log/LogManager.py
bit-online-code-helper/log/__init__.py
bit_online_code_helper/__init__.py
bit_online_code_helper/main.py
bit_online_code_helper/bitonline/BITOnlineManager.py
bit_online_code_helper/bitonline/LocalTestCodeManager.py
bit_online_code_helper/bitonline/LoginManager.py
bit_online_code_helper/bitonline/OnlineTestCodeManager.py
bit_online_code_helper/bitonline/ProblemManager.py
bit_online_code_helper/bitonline/__init__.py
bit_online_code_helper/cli/ArgsParser.py
bit_online_code_helper/cli/__init__.py
bit_online_code_helper/log/LogManager.py
bit_online_code_helper/log/__init__.py
BIT_Online_Code_Helper-1.0.4.dist-info/LICENSE
BIT_Online_Code_Helper-1.0.4.dist-info/METADATA
BIT_Online_Code_Helper-1.0.4.dist-info/WHEEL
BIT_Online_Code_Helper-1.0.4.dist-info/entry_points.txt
BIT_Online_Code_Helper-1.0.4.dist-info/top_level.txt
BIT_Online_Code_Helper-1.0.4.dist-info/RECORD
