Metadata-Version: 2.1
Name: BIT-Online-Code-Helper
Version: 1.0.4
Summary: Test your code of "BIT Online coding homework" more easily and conveniently!
Home-page: https://github.com/Crawler995/BITOnlineCodeHelper
Author: crawler995
Author-email: zhang_995@foxmail.com
License: MIT
Keywords: BIT,code,helper
Platform: UNKNOWN
Classifier: Programming Language :: Python :: 3.7
Requires-Dist: requests
Requires-Dist: tqdm
